ticdat/__init__.py
ticdat/csvtd.py
ticdat/jsontd.py
ticdat/mdb.py
ticdat/model.py
ticdat/pandatfactory.py
ticdat/pandatio.py
ticdat/pgtd.py
ticdat/sqlitetd.py
ticdat/ticdatfactory.py
ticdat/utils.py
ticdat/xls.py
ticdat/testing/__init__.py
ticdat/testing/cogmodel.py
ticdat/testing/delayed_diet.py
ticdat/testing/funky.py
ticdat/testing/funky_diet.py
ticdat/testing/run_tests_for_many.py
ticdat/testing/test_pgtd.py
ticdat/testing/test_slow_bernardo.py
ticdat/testing/testaccdb.py
ticdat/testing/testampl.py
ticdat/testing/testcsv.py
ticdat/testing/testjson.py
ticdat/testing/testmdb.py
ticdat/testing/testmdb_readonly.py
ticdat/testing/testmodel.py
ticdat/testing/testpandas.py
ticdat/testing/testpandat_ampl.py
ticdat/testing/testpandat_io.py
ticdat/testing/testpandat_utils.py
ticdat/testing/testsql.py
ticdat/testing/testutils.py
ticdat/testing/testxls.py
ticdat/testing/ticdattestutils.py
ticdat-0.2.30.dist-info/LICENSE
ticdat-0.2.30.dist-info/METADATA
ticdat-0.2.30.dist-info/WHEEL
ticdat-0.2.30.dist-info/top_level.txt
ticdat-0.2.30.dist-info/RECORD
