Metadata-Version: 2.1
Name: ticdat
Version: 0.2.30
Home-page: https://github.com/ticdat/ticdat/
Author: Pete Cacioppi
Author-email: peter.cacioppi@gmail.com
Maintainer-email: 12samn@gmail.com, Kelley.Shannon.patricia@gmail.com
License: BSD 2-Clause
Platform: any
Classifier: Development Status :: 5 - Production/Stable
Classifier: Intended Audience :: Developers
Classifier: Intended Audience :: Science/Research
Classifier: Operating System :: OS Independent
Classifier: Programming Language :: Python
Classifier: Programming Language :: Python :: 3
Classifier: Topic :: Scientific/Engineering
Classifier: Topic :: Scientific/Engineering :: Mathematics
License-File: LICENSE
